arroba/__init__.py
arroba/datastore_storage.py
arroba/did.py
arroba/diff.py
arroba/firehose.py
arroba/mst.py
arroba/repo.py
arroba/server.py
arroba/storage.py
arroba/util.py
arroba/vis.py
arroba/xrpc_repo.py
arroba/xrpc_server.py
arroba/xrpc_sync.py
arroba/tests/__init__.py
arroba/tests/keyboard.png
arroba/tests/mst_test_suite.py
arroba/tests/snarfed2.car
arroba/tests/snarfed2.json
arroba/tests/test_datastore_storage.py
arroba/tests/test_did.py
arroba/tests/test_diff.py
arroba/tests/test_mst.py
arroba/tests/test_repo.py
arroba/tests/test_storage.py
arroba/tests/test_testdata.py
arroba/tests/test_util.py
arroba/tests/test_xrpc_repo.py
arroba/tests/test_xrpc_server.py
arroba/tests/test_xrpc_sync.py
arroba/tests/testutil.py
arroba/tests/video.mp4
arroba-1.0.dist-info/licenses/LICENSE
mst-test-suite/scripts/generate_exhaustive_cars.py
mst-test-suite/scripts/render_testcase_html.py
arroba-1.0.dist-info/METADATA
arroba-1.0.dist-info/WHEEL
arroba-1.0.dist-info/top_level.txt
arroba-1.0.dist-info/RECORD
