Metadata-Version: 2.4
Name: arroba
Version: 1.0
Summary: Python implementation of Bluesky PDS and AT Protocol, including repo, MST, and sync methods
Author-email: Ryan Barrett <arroba@ryanb.org>
License-Expression: CC0-1.0
Project-URL: Homepage, https://github.com/snarfed/arroba
Project-URL: Documentation, https://arroba.readthedocs.io/
Keywords: arroba,AT Protocol,ATP,Bluesky
Classifier: Programming Language :: Python :: 3
Classifier: Programming Language :: Python :: 3.9
Classifier: Operating System :: OS Independent
Classifier: Intended Audience :: Developers
Classifier: Development Status :: 3 - Alpha
Classifier: Topic :: Software Development :: Libraries :: Python Modules
Requires-Python: >=3.9
License-File: LICENSE
Requires-Dist: cachetools>=5.0
Requires-Dist: carbox>=0.3
Requires-Dist: cryptography>=45.0.0
Requires-Dist: dag-cbor
Requires-Dist: dag-json>=0.2
Requires-Dist: dnspython>=2.0.0
Requires-Dist: lexrpc>=0.8
Requires-Dist: multiformats>=0.3.1
Requires-Dist: pillow
Requires-Dist: pyjwt>=2.0.0
Requires-Dist: pymediainfo
Requires-Dist: simple-websocket
Provides-Extra: datastore
Requires-Dist: google-cloud-ndb>=2.0; extra == "datastore"
Provides-Extra: flask
Requires-Dist: Flask>=2.0; extra == "flask"
Requires-Dist: flask-sock; extra == "flask"
Dynamic: license-file
